AutoScraperX/__init__.py
AutoScraperX/common_spider.py
AutoScraperX/utils.py
AutoScraperX-0.1.2.dist-info/METADATA
AutoScraperX-0.1.2.dist-info/WHEEL
AutoScraperX-0.1.2.dist-info/top_level.txt
AutoScraperX-0.1.2.dist-info/RECORD
