Metadata-Version: 2.1
Name: AutoScraperX
Version: 0.1.2
Summary: A common spider tool based on Selenium
Home-page: https://github.com/chenziying1/AutoScraperX
Author: czy
Author-email: 1060324818@qq.com
Classifier: Programming Language :: Python :: 3
Classifier: Operating System :: OS Independent
Requires-Python: >=3.6
Requires-Dist: selenium
Requires-Dist: beautifulsoup4
Requires-Dist: undetected-chromedriver
